pyscab/DataHandler.py
pyscab/HardwareController.py
pyscab/StimulationController.py
pyscab/__init__.py
pyscab/utils.py
tests/__init__.py
tests/main.py
tests/show_devices.py
pyscab-1.0.1.dist-info/LICENSE
pyscab-1.0.1.dist-info/METADATA
pyscab-1.0.1.dist-info/WHEEL
pyscab-1.0.1.dist-info/top_level.txt
pyscab-1.0.1.dist-info/RECORD
