Metadata-Version: 2.1
Name: pyscab
Version: 1.0.1
Summary: python implementation of scab (stimulation controller for auditory brain-computer interface)
Home-page: https://github.com/simonkojima/scab-python
Author: Simon Kojima
Author-email: simon.kojima@outlook.com
Project-URL: Bug Tracker, https://github.com/simonkojima/scab-python/issues
Classifier: Programming Language :: Python :: 3
Classifier: License :: OSI Approved :: MIT License
Classifier: Operating System :: OS Independent
Requires-Python: >=3.6
License-File: LICENSE
Requires-Dist: pyaudio (>=0.2.11)
Requires-Dist: numpy (>=1.15.4)
